prlps_ipinfo/__init__.py
prlps_ipinfo/ipinfo.py
prlps_ipinfo-0.0.1b0.dist-info/LICENSE.txt
prlps_ipinfo-0.0.1b0.dist-info/METADATA
prlps_ipinfo-0.0.1b0.dist-info/WHEEL
prlps_ipinfo-0.0.1b0.dist-info/top_level.txt
prlps_ipinfo-0.0.1b0.dist-info/RECORD
