Metadata-Version: 2.1
Name: prlps_ipinfo
Version: 0.0.1b0
Summary: получение подробной информации о ip, с поддержкой прокси
Home-page: https://github.com/prolapser/prlps_ipinfo
Author: prolapser
License: LICENSE.txt
Classifier: Development Status :: 4 - Beta
Classifier: Intended Audience :: Developers
Classifier: License :: OSI Approved :: MIT License
Classifier: Operating System :: OS Independent
Requires-Python: >=3.10
License-File: LICENSE.txt
Requires-Dist: httpx
Requires-Dist: httpx-socks
